terminut/__init__.py
terminut/colors.py
terminut/console.py
terminut/legacy.py
terminut/log.py
terminut/unique.py
terminut-0.0.0.940.dist-info/LICENSE
terminut-0.0.0.940.dist-info/METADATA
terminut-0.0.0.940.dist-info/WHEEL
terminut-0.0.0.940.dist-info/top_level.txt
terminut-0.0.0.940.dist-info/RECORD
