Metadata-Version: 2.1
Name: terminut
Version: 0.0.0.940
Summary: Terminut // @imvast
Home-page: http://pypi.python.org/pypi/terminut
Author: @imvast
Author-email: dev@vast.sh
License: MIT
Project-URL: Homepage, https://github.com/imvast/terminut
Project-URL: Suggestions, https://github.com/imvast/terminut/issues
Classifier: Development Status :: 3 - Alpha
Classifier: Intended Audience :: Developers
Classifier: License :: OSI Approved :: MIT License
Classifier: Natural Language :: English
Classifier: Programming Language :: Python
Classifier: Programming Language :: Python :: 3
Classifier: Programming Language :: Python :: 3.8
Classifier: Programming Language :: Python :: 3.9
Classifier: Programming Language :: Python :: 3.10
Classifier: Programming Language :: Python :: 3.11
Classifier: Topic :: Scientific/Engineering
Classifier: Topic :: Scientific/Engineering :: Information Analysis
Classifier: Topic :: Scientific/Engineering :: Mathematics
Classifier: Topic :: Scientific/Engineering :: Visualization
Classifier: Topic :: Software Development :: Libraries
Classifier: Topic :: Utilities
Requires-Python: ~=3.8
License-File: LICENSE
Requires-Dist: colorama >=0.4.6
Requires-Dist: requests >=2.30.0
